[
  { "stage": 1, "targetDurationSeconds": 30, "keyUpgrade": "어묵 레시피 I", "startRevenuePerSecond": 3.2, "exitRevenuePerSecond": 5.82, "totalBudget": 132, "purchaseCosts": [8, 12, 17, 22, 30, 42], "baseSpawnIntervalMs": 6000, "basePatienceMs": 32000, "seatCount": 2, "chefCount": 0, "serverCount": 0 },
  { "stage": 2, "targetDurationSeconds": 50, "keyUpgrade": "접이식 의자", "startRevenuePerSecond": 5.82, "exitRevenuePerSecond": 10.6, "totalBudget": 400, "purchaseCosts": [24, 36, 52, 68, 92, 128], "baseSpawnIntervalMs": 5700, "basePatienceMs": 31000, "seatCount": 3, "chefCount": 0, "serverCount": 0 },
  { "stage": 3, "targetDurationSeconds": 70, "keyUpgrade": "빠른 냄비 I", "startRevenuePerSecond": 10.6, "exitRevenuePerSecond": 19.2, "totalBudget": 1020, "purchaseCosts": [61, 92, 132, 173, 234, 326], "baseSpawnIntervalMs": 5400, "basePatienceMs": 30000, "seatCount": 3, "chefCount": 0, "serverCount": 0 },
  { "stage": 4, "targetDurationSeconds": 90, "keyUpgrade": "셰프 1호", "startRevenuePerSecond": 19.2, "exitRevenuePerSecond": 34.9, "totalBudget": 2380, "purchaseCosts": [143, 214, 310, 405, 548, 762], "baseSpawnIntervalMs": 5100, "basePatienceMs": 29000, "seatCount": 3, "chefCount": 1, "serverCount": 0 },
  { "stage": 5, "targetDurationSeconds": 120, "keyUpgrade": "어묵 명물화", "startRevenuePerSecond": 34.9, "exitRevenuePerSecond": 63.5, "totalBudget": 5770, "purchaseCosts": [346, 520, 751, 981, 1330, 1850], "baseSpawnIntervalMs": 4800, "basePatienceMs": 28000, "seatCount": 3, "chefCount": 1, "serverCount": 0 },
  { "stage": 6, "targetDurationSeconds": 240, "keyUpgrade": "떡볶이 해금", "startRevenuePerSecond": 63.5, "exitRevenuePerSecond": 115, "totalBudget": 21000, "purchaseCosts": [1260, 1890, 2730, 3570, 4830, 6720], "baseSpawnIntervalMs": 4600, "basePatienceMs": 28000, "seatCount": 3, "chefCount": 1, "serverCount": 0 },
  { "stage": 7, "targetDurationSeconds": 240, "keyUpgrade": "서빙 알바 1호", "startRevenuePerSecond": 115, "exitRevenuePerSecond": 210, "totalBudget": 38200, "purchaseCosts": [2290, 3430, 4960, 6490, 8780, 12200], "baseSpawnIntervalMs": 4400, "basePatienceMs": 27000, "seatCount": 3, "chefCount": 1, "serverCount": 1 },
  { "stage": 8, "targetDurationSeconds": 240, "keyUpgrade": "천막 확장 I", "startRevenuePerSecond": 210, "exitRevenuePerSecond": 382, "totalBudget": 69400, "purchaseCosts": [4160, 6240, 9020, 11800, 16000, 22200], "baseSpawnIntervalMs": 4200, "basePatienceMs": 27000, "seatCount": 5, "chefCount": 1, "serverCount": 1 },
  { "stage": 9, "targetDurationSeconds": 240, "keyUpgrade": "손님 피버 Lv.1", "startRevenuePerSecond": 382, "exitRevenuePerSecond": 694, "totalBudget": 126000, "purchaseCosts": [7560, 11300, 16400, 21400, 29000, 40300], "baseSpawnIntervalMs": 4000, "basePatienceMs": 26000, "seatCount": 5, "chefCount": 1, "serverCount": 1 },
  { "stage": 10, "targetDurationSeconds": 240, "keyUpgrade": "떡볶이 명물화", "startRevenuePerSecond": 694, "exitRevenuePerSecond": 1260, "totalBudget": 229000, "purchaseCosts": [13800, 20600, 29800, 39000, 52700, 73300], "baseSpawnIntervalMs": 3800, "basePatienceMs": 25000, "seatCount": 5, "chefCount": 1, "serverCount": 1 },
  { "stage": 11, "targetDurationSeconds": 480, "keyUpgrade": "붕어빵 해금", "startRevenuePerSecond": 1260, "exitRevenuePerSecond": 2290, "totalBudget": 833000, "purchaseCosts": [50000, 75000, 108000, 142000, 192000, 267000], "baseSpawnIntervalMs": 3600, "basePatienceMs": 24000, "seatCount": 5, "chefCount": 1, "serverCount": 1 },
  { "stage": 12, "targetDurationSeconds": 480, "keyUpgrade": "셰프 2호", "startRevenuePerSecond": 2290, "exitRevenuePerSecond": 4170, "totalBudget": 1510000, "purchaseCosts": [90900, 136000, 197000, 257000, 348000, 485000], "baseSpawnIntervalMs": 3450, "basePatienceMs": 23000, "seatCount": 5, "chefCount": 2, "serverCount": 1 },
  { "stage": 13, "targetDurationSeconds": 480, "keyUpgrade": "홀 확장 I", "startRevenuePerSecond": 4170, "exitRevenuePerSecond": 7570, "totalBudget": 2750000, "purchaseCosts": [165000, 248000, 358000, 468000, 633000, 881000], "baseSpawnIntervalMs": 3300, "basePatienceMs": 23000, "seatCount": 7, "chefCount": 2, "serverCount": 1 },
  { "stage": 14, "targetDurationSeconds": 480, "keyUpgrade": "서빙 알바 2호", "startRevenuePerSecond": 7570, "exitRevenuePerSecond": 13800, "totalBudget": 5010000, "purchaseCosts": [300000, 450000, 651000, 851000, 1150000, 1600000], "baseSpawnIntervalMs": 3150, "basePatienceMs": 22000, "seatCount": 7, "chefCount": 2, "serverCount": 2 },
  { "stage": 15, "targetDurationSeconds": 480, "keyUpgrade": "붕어빵 명물화", "startRevenuePerSecond": 13800, "exitRevenuePerSecond": 25000, "totalBudget": 9100000, "purchaseCosts": [546000, 819000, 1180000, 1550000, 2090000, 2910000], "baseSpawnIntervalMs": 3000, "basePatienceMs": 21000, "seatCount": 7, "chefCount": 2, "serverCount": 2 },
  { "stage": 16, "targetDurationSeconds": 720, "keyUpgrade": "야식 라면 해금", "startRevenuePerSecond": 25000, "exitRevenuePerSecond": 45500, "totalBudget": 24800000, "purchaseCosts": [1490000, 2230000, 3230000, 4220000, 5710000, 7940000], "baseSpawnIntervalMs": 2900, "basePatienceMs": 20000, "seatCount": 7, "chefCount": 2, "serverCount": 2 },
  { "stage": 17, "targetDurationSeconds": 720, "keyUpgrade": "고압 화구", "startRevenuePerSecond": 45500, "exitRevenuePerSecond": 82700, "totalBudget": 45100000, "purchaseCosts": [2710000, 4060000, 5860000, 7670000, 10400000, 14400000], "baseSpawnIntervalMs": 2800, "basePatienceMs": 19000, "seatCount": 7, "chefCount": 2, "serverCount": 2 },
  { "stage": 18, "targetDurationSeconds": 720, "keyUpgrade": "홀 확장 II + 피버 Lv.2", "startRevenuePerSecond": 82700, "exitRevenuePerSecond": 150000, "totalBudget": 82000000, "purchaseCosts": [4920000, 7380000, 10700000, 13900000, 18900000, 26200000], "baseSpawnIntervalMs": 2700, "basePatienceMs": 19000, "seatCount": 9, "chefCount": 2, "serverCount": 2 },
  { "stage": 19, "targetDurationSeconds": 720, "keyUpgrade": "셰프 3호", "startRevenuePerSecond": 150000, "exitRevenuePerSecond": 273000, "totalBudget": 149000000, "purchaseCosts": [8940000, 13400000, 19400000, 25300000, 34300000, 47700000], "baseSpawnIntervalMs": 2600, "basePatienceMs": 18000, "seatCount": 9, "chefCount": 3, "serverCount": 2 },
  { "stage": 20, "targetDurationSeconds": 720, "keyUpgrade": "라면 명물화", "startRevenuePerSecond": 273000, "exitRevenuePerSecond": 497000, "totalBudget": 271000000, "purchaseCosts": [16300000, 24400000, 35200000, 46100000, 62300000, 86700000], "baseSpawnIntervalMs": 2500, "basePatienceMs": 17000, "seatCount": 9, "chefCount": 3, "serverCount": 2 },
  { "stage": 21, "targetDurationSeconds": 1020, "keyUpgrade": "달빛 꼬치 해금", "startRevenuePerSecond": 497000, "exitRevenuePerSecond": 903000, "totalBudget": 698000000, "purchaseCosts": [41900000, 62800000, 90700000, 119000000, 160000000, 223000000], "baseSpawnIntervalMs": 2350, "basePatienceMs": 17000, "seatCount": 9, "chefCount": 3, "serverCount": 2 },
  { "stage": 22, "targetDurationSeconds": 1020, "keyUpgrade": "서빙 알바 3호", "startRevenuePerSecond": 903000, "exitRevenuePerSecond": 1640000, "totalBudget": 1270000000, "purchaseCosts": [76100000, 114000000, 165000000, 216000000, 292000000, 406000000], "baseSpawnIntervalMs": 2250, "basePatienceMs": 16000, "seatCount": 9, "chefCount": 3, "serverCount": 3 },
  { "stage": 23, "targetDurationSeconds": 1020, "keyUpgrade": "메뉴 홍보·VIP 해금", "startRevenuePerSecond": 1640000, "exitRevenuePerSecond": 2980000, "totalBudget": 2310000000, "purchaseCosts": [138000000, 207000000, 300000000, 392000000, 530000000, 738000000], "baseSpawnIntervalMs": 2150, "basePatienceMs": 15000, "seatCount": 9, "chefCount": 3, "serverCount": 3 },
  { "stage": 24, "targetDurationSeconds": 1020, "keyUpgrade": "야외 좌석", "startRevenuePerSecond": 2980000, "exitRevenuePerSecond": 5420000, "totalBudget": 4190000000, "purchaseCosts": [251000000, 377000000, 545000000, 712000000, 964000000, 1340000000], "baseSpawnIntervalMs": 2050, "basePatienceMs": 15000, "seatCount": 12, "chefCount": 3, "serverCount": 3 },
  { "stage": 25, "targetDurationSeconds": 1020, "keyUpgrade": "꼬치 명물화 + 러시", "startRevenuePerSecond": 5420000, "exitRevenuePerSecond": 9860000, "totalBudget": 7620000000, "purchaseCosts": [457000000, 686000000, 990000000, 1290000000, 1750000000, 2440000000], "baseSpawnIntervalMs": 1950, "basePatienceMs": 14000, "seatCount": 12, "chefCount": 3, "serverCount": 3 },
  { "stage": 26, "targetDurationSeconds": 1200, "keyUpgrade": "달빛 정식 해금", "startRevenuePerSecond": 9860000, "exitRevenuePerSecond": 17900000, "totalBudget": 16300000000, "purchaseCosts": [977000000, 1470000000, 2120000000, 2770000000, 3750000000, 5210000000], "baseSpawnIntervalMs": 1850, "basePatienceMs": 14000, "seatCount": 12, "chefCount": 3, "serverCount": 3 },
  { "stage": 27, "targetDurationSeconds": 1500, "keyUpgrade": "셰프 4호", "startRevenuePerSecond": 17900000, "exitRevenuePerSecond": 32600000, "totalBudget": 37000000000, "purchaseCosts": [2220000000, 3330000000, 4810000000, 6290000000, 8510000000, 11800000000], "baseSpawnIntervalMs": 1750, "basePatienceMs": 13000, "seatCount": 12, "chefCount": 4, "serverCount": 3 },
  { "stage": 28, "targetDurationSeconds": 1800, "keyUpgrade": "서빙 알바 4호", "startRevenuePerSecond": 32600000, "exitRevenuePerSecond": 59200000, "totalBudget": 80700000000, "purchaseCosts": [4840000000, 7270000000, 10500000000, 13700000000, 18600000000, 25800000000], "baseSpawnIntervalMs": 1650, "basePatienceMs": 13000, "seatCount": 12, "chefCount": 4, "serverCount": 4 },
  { "stage": 29, "targetDurationSeconds": 2100, "keyUpgrade": "올나이트 확장 + 피버 Lv.3", "startRevenuePerSecond": 59200000, "exitRevenuePerSecond": 108000000, "totalBudget": 171000000000, "purchaseCosts": [10300000000, 15400000000, 22300000000, 29100000000, 39400000000, 54800000000], "baseSpawnIntervalMs": 1600, "basePatienceMs": 12000, "seatCount": 14, "chefCount": 4, "serverCount": 4 },
  { "stage": 30, "targetDurationSeconds": 3600, "keyUpgrade": "달빛 간판 5부품", "startRevenuePerSecond": 108000000, "exitRevenuePerSecond": 190000000, "totalBudget": 492000000000, "purchaseCosts": [77500000000, 86800000000, 97200000000, 109000000000, 122000000000], "baseSpawnIntervalMs": 1550, "basePatienceMs": 11000, "seatCount": 14, "chefCount": 4, "serverCount": 4 }
]
